lucina/__init__.py
lucina/__main__.py
lucina/cell.py
lucina/format.py
lucina/parser.py
lucina/utils.py
lucina-1.0.1.dist-info/METADATA
lucina-1.0.1.dist-info/WHEEL
lucina-1.0.1.dist-info/entry_points.txt
lucina-1.0.1.dist-info/top_level.txt
lucina-1.0.1.dist-info/RECORD
