Metadata-Version: 2.1
Name: lucina
Version: 1.0.1
Summary: From markdown to Jupyter notebook
Author-email: entwanne <antoine.rozo@gmail.com>
License: MIT License
Project-URL: homepage, https://github.com/entwanne/lucina
Classifier: Development Status :: 5 - Production/Stable
Classifier: Programming Language :: Python :: 3
Classifier: License :: OSI Approved :: MIT License
Requires-Dist: minimd ==1.*
Provides-Extra: dev
Requires-Dist: pytest ; extra == 'dev'
Requires-Dist: pytest-mock ; extra == 'dev'
Requires-Dist: flake8 ; extra == 'dev'
Requires-Dist: isort ; extra == 'dev'
